parrec/__init__.py
parrec/parread.py
parrec/recread.py
parrec_reader_py-0.1.0.dist-info/LICENSE
parrec_reader_py-0.1.0.dist-info/METADATA
parrec_reader_py-0.1.0.dist-info/WHEEL
parrec_reader_py-0.1.0.dist-info/top_level.txt
parrec_reader_py-0.1.0.dist-info/RECORD
