Metadata-Version: 2.1
Name: parrec-reader-py
Version: 0.1.0
Summary: A Philips par/rec reader for Python
Home-page: https://github.com/gyrotools/parrec-reader-py
Author: Martin Bührer
Author-email: info@gyrotools.com
Classifier: Programming Language :: Python :: 3
Classifier: License :: OSI Approved :: MIT License
Classifier: Operating System :: OS Independent
Requires-Python: >=3.6.0
License-File: LICENSE
Requires-Dist: numpy
